MusicInsights/Waveform.py
MusicInsights/__init__.py
MusicInsights/utils.py
MusicInsights-1.0.dist-info/LICENSE
MusicInsights-1.0.dist-info/METADATA
MusicInsights-1.0.dist-info/WHEEL
MusicInsights-1.0.dist-info/top_level.txt
MusicInsights-1.0.dist-info/RECORD
