Metadata-Version: 2.1
Name: MusicInsights
Version: 1.0
License: This is free and unencumbered software released into the public domain.
Project-URL: Repository, https://github.com/nip403/Music-Video-Sound-Analysis/tree/main
Requires-Python: >=3.8
License-File: LICENSE
Requires-Dist: numpy
Requires-Dist: librosa ==0.10.1
Requires-Dist: matplotlib
Requires-Dist: sounddevice ==0.4.6
